drb/drivers/aws3/__init__.py
drb/drivers/aws3/_version.py
drb/drivers/aws3/aws3.py
drb/topics/aws3/__init__.py
drb/topics/aws3/cortex.yml
drb_driver_s3-1.3.2.dist-info/LICENCE.txt
drb_driver_s3-1.3.2.dist-info/METADATA
drb_driver_s3-1.3.2.dist-info/WHEEL
drb_driver_s3-1.3.2.dist-info/entry_points.txt
drb_driver_s3-1.3.2.dist-info/top_level.txt
drb_driver_s3-1.3.2.dist-info/RECORD
