Metadata-Version: 2.1
Name: drb-driver-s3
Version: 1.3.2
Summary: DRB aws3 driver
Author: GAEL Systems
Author-email: drb-python@gael.fr
License: LGPLv3
Project-URL: Documentation, http://drb-python.gitlab.io/impl/aws3
Project-URL: Source, https://gitlab.com/drb-python/impl/aws3
Classifier: Programming Language :: Python :: 3.8
Classifier: Environment :: Plugins
Classifier: License :: OSI Approved :: GNU Lesser General Public License v3 (LGPLv3)
Requires-Python: >=3.8
License-File: LICENCE.txt
Requires-Dist: drb ~=2.2.0
Requires-Dist: drb-driver-http ~=1.3.0
Requires-Dist: boto3 ~=1.28.69
Requires-Dist: botocore ~=1.31.69
